minimal_diffsl-0.1.0.dist-info/METADATA
minimal_diffsl-0.1.0.dist-info/WHEEL
minimal_diffsl/__init__.py
minimal_diffsl/minimal_diffsl.cp39-win_amd64.pyd
minimal_diffsl-0.1.0.dist-info/RECORD
